<DOMSymbolItem xmlns:xsi="http://www.w3.org/2001/XMLSchema-instance" xmlns="http://ns.adobe.com/xfl/2008/" name="SystemConsole/CommandCard/CommandCard" itemID="5e92442b-0000022a" linkageExportForAS="true" linkageClassName="CommandCard" lastModified="1586659831">
  <timeline>
    <DOMTimeline name="CommandCard" layerDepthEnabled="true">
      <layers>
        <DOMLayer name="SelectedScript_tf" color="#FF800A" locked="true" autoNamed="false">
          <frames>
            <DOMFrame index="0" keyMode="9728">
              <elements>
                <DOMDynamicText name="SelectedScript_tf" width="529.8" height="28.8" lineType="multiline">
                  <matrix>
                    <Matrix tx="2.1" ty="73.2"/>
                  </matrix>
                  <textRuns>
                    <DOMTextRun>
                      <characters>SelectedScript_tf</characters>
                      <textAttrs>
                        <DOMTextAttrs alignment="center" aliasText="false" lineHeight="28.8" size="24" bitmapSize="480" face="$MAIN_Font*"/>
                      </textAttrs>
                    </DOMTextRun>
                  </textRuns>
                </DOMDynamicText>
              </elements>
            </DOMFrame>
          </frames>
        </DOMLayer>
        <DOMLayer name="SelectedName_tf" color="#FF4FFF" locked="true" autoNamed="false">
          <frames>
            <DOMFrame index="0" keyMode="9728">
              <elements>
                <DOMDynamicText name="SelectedName_tf" width="533.8" height="28.8" lineType="multiline">
                  <matrix>
                    <Matrix tx="2.1" ty="125.2"/>
                  </matrix>
                  <textRuns>
                    <DOMTextRun>
                      <characters>SelectedName_tf</characters>
                      <textAttrs>
                        <DOMTextAttrs alignment="center" aliasText="false" lineHeight="28.8" size="24" bitmapSize="480" face="$MAIN_Font*"/>
                      </textAttrs>
                    </DOMTextRun>
                  </textRuns>
                </DOMDynamicText>
              </elements>
            </DOMFrame>
          </frames>
        </DOMLayer>
        <DOMLayer name="SelectedDescription_tf" color="#009999" locked="true" autoNamed="false">
          <frames>
            <DOMFrame index="0" keyMode="9728">
              <elements>
                <DOMDynamicText name="SelectedDescription_tf" width="529.8" height="28.8" lineType="multiline">
                  <matrix>
                    <Matrix tx="2.1" ty="171.2"/>
                  </matrix>
                  <textRuns>
                    <DOMTextRun>
                      <characters>SelectedDescription_tf</characters>
                      <textAttrs>
                        <DOMTextAttrs alignment="center" aliasText="false" lineHeight="28.8" size="24" bitmapSize="480" face="$MAIN_Font*"/>
                      </textAttrs>
                    </DOMTextRun>
                  </textRuns>
                </DOMDynamicText>
              </elements>
            </DOMFrame>
          </frames>
        </DOMLayer>
        <DOMLayer name="Layer_8" color="#FF4F4F" current="true" isSelected="true">
          <frames>
            <DOMFrame index="0" keyMode="9728">
              <elements/>
            </DOMFrame>
          </frames>
        </DOMLayer>
        <DOMLayer name="Background_Shape" color="#FF0000" locked="true" autoNamed="false">
          <frames>
            <DOMFrame index="0" keyMode="9728">
              <elements>
                <DOMShape>
                  <fills>
                    <FillStyle index="1">
                      <SolidColor color="#CC0000" alpha="0.2"/>
                    </FillStyle>
                  </fills>
                  <strokes>
                    <StrokeStyle index="1">
                      <SolidStroke scaleMode="normal">
                        <fill>
                          <SolidColor/>
                        </fill>
                      </SolidStroke>
                    </StrokeStyle>
                  </strokes>
                  <edges>
                    <Edge fillStyle1="1" strokeStyle="1" edges="!0 -6|10671 -6!10671 -6|10671 5781!10671 5781|0 5781!0 5781|0 -6"/>
                    <Edge cubics="!0 -6(;0,-6 10671,-6 10671,-6q0 -6 10671 -6);"/>
                    <Edge cubics="!10671 -6(;10671,-6 10671,5781 10671,5781q10671 -6 10671 5781);"/>
                    <Edge cubics="!10671 5781(;10671,5781 0,5781 0,5781q10671 5781 0 5781);"/>
                    <Edge cubics="!0 5781(;0,5781 0,-6 0,-6q0 5781 0 -6);"/>
                  </edges>
                </DOMShape>
              </elements>
            </DOMFrame>
          </frames>
        </DOMLayer>
      </layers>
    </DOMTimeline>
  </timeline>
</DOMSymbolItem>