<DOMSymbolItem xmlns:xsi="http://www.w3.org/2001/XMLSchema-instance" xmlns="http://ns.adobe.com/xfl/2008/" name="Symbol 134" itemID="5dc01bf0-00000060" linkageExportForAS="true" linkageClassName="RightHandList" lastModified="1571730685">
  <timeline>
    <DOMTimeline name="Symbol 134">
      <layers>
        <DOMLayer name="Layer 1" color="#72DCFF">
          <frames>
            <DOMFrame index="0" keyMode="9728">
              <elements>
                <DOMSymbolInstance libraryItemName="Symbol 49" name="ScrollDown" centerPoint3DX="8.95" centerPoint3DY="113.5">
                  <matrix>
                    <Matrix a="0" b="1.99998474121094" c="-0.571426391601563" d="0" tx="6" ty="104.05"/>
                  </matrix>
                  <transformationPoint>
                    <Point/>
                  </transformationPoint>
                </DOMSymbolInstance>
              </elements>
            </DOMFrame>
          </frames>
        </DOMLayer>
        <DOMLayer name="Layer 2" color="#F27FAC">
          <frames>
            <DOMFrame index="0" keyMode="9728">
              <elements>
                <DOMSymbolInstance libraryItemName="Symbol 49" name="ScrollUp" centerPoint3DX="-1.05" centerPoint3DY="26.4">
                  <matrix>
                    <Matrix a="0" b="-1.99998474121094" c="0.571426391601563" d="0" tx="-4" ty="16.95"/>
                  </matrix>
                  <transformationPoint>
                    <Point/>
                  </transformationPoint>
                </DOMSymbolInstance>
              </elements>
            </DOMFrame>
          </frames>
        </DOMLayer>
        <DOMLayer name="Layer 3" color="#A96379" current="true" isSelected="true">
          <frames>
            <DOMFrame index="0" keyMode="9728">
              <elements>
                <DOMSymbolInstance libraryItemName="Symbol 15" name="border" centerPoint3DX="50.5" centerPoint3DY="51.5">
                  <matrix>
                    <Matrix a="1.99998474121094" d="1.717041015625" ty="1"/>
                  </matrix>
                  <transformationPoint>
                    <Point/>
                  </transformationPoint>
                  <color>
                    <Color alphaMultiplier="0"/>
                  </color>
                </DOMSymbolInstance>
              </elements>
            </DOMFrame>
          </frames>
        </DOMLayer>
      </layers>
    </DOMTimeline>
  </timeline>
</DOMSymbolItem>